pouty/__init__.py
pouty/iostream.py
pouty/stdlib/__init__.py
pouty/stdlib/h.py
pouty-1.0.0.dist-info/WHEEL
pouty-1.0.0.dist-info/METADATA
pouty-1.0.0.dist-info/RECORD
