Metadata-Version: 2.1
Name: pouty
Version: 1.0.0
Summary: C++-style IO in Python!
Author: Om Duggineni
Author-email: omduggineni@gmail.com
Requires-Python: >=3.7,<4.0
Classifier: Programming Language :: Python :: 3
Classifier: Programming Language :: Python :: 3.7
Classifier: Programming Language :: Python :: 3.8
Classifier: Programming Language :: Python :: 3.9
Classifier: Programming Language :: Python :: 3.10
